Metadata-Version: 1.0
Name: gaussian-binomial-probabilities
Version: 1.0
Summary: Gaussian and Binomial Distributions
Home-page: UNKNOWN
Author: Angel Ivanov
Author-email: angel.iwanov@gmail.com
License: UNKNOWN
Platform: UNKNOWN
